LICENSE
README.md
setup.py
pnrw/__init__.py
pnrw/convert.py
pnrw/exceptions.py
pnrw/pnrwf.py
pnrw.egg-info/PKG-INFO
pnrw.egg-info/SOURCES.txt
pnrw.egg-info/dependency_links.txt
pnrw.egg-info/top_level.txt