Metadata-Version: 2.1
Name: pnrw
Version: 0.1.4
Summary: Python Nanocurrency RPC Wrapper
Home-page: https://github.com/MiranDaniel/pnrw
Author: MiranDaniel
Author-email: mirandaniel@protonmail.com
License: License :: OSI Approved :: GNU General Public License v3 (GPLv3)
Platform: UNKNOWN
Classifier: Environment :: Console
Classifier: Operating System :: OS Independent
Classifier: Programming Language :: Python :: 3
Requires-Python: >=3.6
